dc_api.py
dc_api-0.8.0.dist-info/LICENSE
dc_api-0.8.0.dist-info/METADATA
dc_api-0.8.0.dist-info/WHEEL
dc_api-0.8.0.dist-info/entry_points.txt
dc_api-0.8.0.dist-info/top_level.txt
dc_api-0.8.0.dist-info/RECORD
