Metadata-Version: 2.1
Name: dc-api
Version: 0.8.0
Summary: Deadly dimple unofficial dcinside api
Home-page: https://github.com/song9446/dcinside-python3-api
Author: Eunchul, Song
Author-email: eunchulsong9@gmail.com
License: UNKNOWN
Platform: UNKNOWN
Classifier: Programming Language :: Python :: 3
Classifier: License :: OSI Approved :: MIT License
Classifier: Operating System :: OS Independent
License-File: LICENSE
Requires-Dist: lxml
Requires-Dist: aiohttp
Requires-Dist: tenacity
